MANIFEST.in
README.rst
VERSION
setup.py
setup_completeme_key_binding.sh
completeme/__init__.py
completeme/collection.py
completeme/completeme.py
completeme/search.py
completeme/utils.py
completeme.egg-info/PKG-INFO
completeme.egg-info/SOURCES.txt
completeme.egg-info/dependency_links.txt
completeme.egg-info/entry_points.txt
completeme.egg-info/requires.txt
completeme.egg-info/top_level.txt
completeme/conf/completeme.json