Metadata-Version: 1.0
Name: completeme
Version: 0.5.10
Summary: Automagic ctrl+t filename completion to launch in your favorite editor
Home-page: https://github.com/mattspitz/completeme
Author: Matt Spitz
Author-email: mattspitz@gmail.com
License: UNKNOWN
Platform: UNKNOWN
